Workbook

Sheet Instructions
A1: Oracle Fusion Financials — Client Discovery & Product Mapping Workbook
A2: Covers Core Financials: General Ledger (GL), Accounts Payable (AP), Accounts Receivable (AR), Fixed Assets (FA), Cash Management (CM)
A4: THREE-PHASE STRUCTURE
A5: Built around a client who just called and you're starting from zero:
A7: Phase 1 - Client Intake Who they are: company, contacts, current systems, why they're calling.
A8: Answerable in the first few minutes of the first call.
A9: Phase 2 - Needs & Wants The 6 scope-qualifier questions. Establishes which modules (GL/AP/AR/FA/CM)
A10: are actually in play before you go deep on any of them.
A11: Phase 3 - Detailed Discovery The module-specific configuration questions. These typically can't be
A12: fully answered on the first call -- expect to fill these in over follow-up
A13: sessions with the right stakeholders on the client side.
A15: Live client tracking happens in INSIGHT_All_Clients_Roster.xlsx — one row per client, not one file per client (that draft convention is retired).
... A46: review and edit before using this with a client.

Sheet Discovery Questions
A1: Question ID | B1: Phase | C1: Module | D1: Functional Area | E1: Question | F1: Type | G1: Required | H1: Client Answer | I1: Status
A2: INTAKE-001 | B2: 1 – Client Intake | C2: INTAKE | D2: Client Identification | E2: What is the client's full legal company name, and what should we call them informally? | F2: Free Text | G2: Y | I2: =IF(TRIM(H2)<>"","✓ Answered",IF(G2="Y","⚠ Missing – AI Follow-Up","— Optional (not answered)"))
A3: INTAKE-002 | B3: 1 – Client Intake | C3: INTAKE | D3: Client Identification | E3: Who is the primary contact for this engagement (name, title, email, phone)? | F3: Free Text | G3: Y | I3: =IF(TRIM(H3)<>"","✓ Answered",IF(G3="Y","⚠ Missing – AI Follow-Up","— Optional (not answered)"))
A4: INTAKE-003 | B4: 1 – Client Intake | C4: INTAKE | D4: Client Identification | E4: Who else should be considered a key stakeholder or decision-maker (e.g., CFO, Controller, IT Director)? | F4: Free Text | G4: N | I4: =IF(TRIM(H4)<>"","✓ Answered",IF(G4="Y","⚠ Missing – AI Follow-Up","— Optional (not answered)"))
A5: INTAKE-004 | B5: 1 – Client Intake | C5: INTAKE | D5: Company Profile | E5: What industry/sector is the client in, and approximately how large are they (employee count and/or annual revenue)? | F5: Free Text | G5: Y | I5: =IF(TRIM(H5)<>"","✓ Answered",IF(G5="Y","⚠ Missing – AI Follow-Up","— Optional (not answered)"))
A6: INTAKE-005 | B6: 1 – Client Intake | C6: INTAKE | D6: Company Profile | E6: Roughly how many legal entities, subsidiaries, or locations does the client operate? | F6: Free Text | G6: N | I6: =IF(TRIM(H6)<>"","✓ Answered",IF(G6="Y","⚠ Missing – AI Follow-Up","— Optional (not answered)"))
A7: INTAKE-006 | B7: 1 – Client Intake | C7: INTAKE | D7: Current Environment | E7: What ERP or financial system(s) is the client currently using, and are they still under contract/support? | F7: Free Text | G7: Y | I7: =IF(TRIM(H7)<>"","✓ Answered",IF(G7="Y","⚠ Missing – AI Follow-Up","— Optional (not answered)"))
A8: INTAKE-007 | B8: 1 – Client Intake | C8: INTAKE | D8: Current Environment | E8: Are there other systems already in place that will need to integrate with Oracle Fusion (e.g., payroll, procurement, banking, CRM)? | F8: Free Text | G8: N | I8: =IF(TRIM(H8)<>"","✓ Answered",IF(G8="Y","⚠ Missing – AI Follow-Up","— Optional (not answered)"))
A9: INTAKE-008 | B9: 1 – Client Intake | C9: INTAKE | D9: Reason for Engagement | E9: What prompted the client to reach out now (e.g., system end-of-life, growth, compliance, M&A, dissatisfaction with current provider)? | F9: Free Text | G9: Y | I9: =IF(TRIM(H9)<>"","✓ Answered",IF(G9="Y","⚠ Missing – AI Follow-Up","— Optional (not answered)"))
A10: INTAKE-009 | B10: 1 – Client Intake | C10: INTAKE | D10: Reason for Engagement | E10: What does the client consider their biggest pain point today? | F10: Free Text | G10: N | I10: =IF(TRIM(H10)<>"","✓ Answered",IF(G10="Y","⚠ Missing – AI Follow-Up","— Optional (not answered)"))
A11: INTAKE-010 | B11: 1 – Client Intake | C11: INTAKE | D11: Timeline & Constraints | E11: Is there a target go-live date or an external deadline driving the timeline (e.g., fiscal year-end, contract expiration)? | F11: Free Text | G11: N | I11: =IF(TRIM(H11)<>"","✓ Answered",IF(G11="Y","⚠ Missing – AI Follow-Up","— Optional (not answered)"))
A12: QUAL-GL | B12: 2 – Needs & Wants (Scope) | C12: GL | D12: Module Scoping | E12: Is General Ledger required as the core financial system of record? (GL is the foundation module for every Fusion Financials implementation and is always in scope.) | F12: Yes/No | G12: Y | H12: Yes | I12: =IF(TRIM(H12)<>"","✓ Answered","⚠ Missing – AI Follow-Up")
A13: QUAL-AP | B13: 2 – Needs & Wants (Scope) | C13: AP | D13: Module Scoping | E13: Does the organization process vendor/supplier invoices and issue payments to suppliers? | F13: Yes/No | G13: Y | I13: =IF(TRIM(H13)<>"","✓ Answered","⚠ Missing – AI Follow-Up")
A14: QUAL-AR | B14: 2 – Needs & Wants (Scope) | C14: AR | D14: Module Scoping | E14: Does the organization invoice customers and manage receivables, collections, or billing? | F14: Yes/No | G14: Y | I14: =IF(TRIM(H14)<>"","✓ Answered","⚠ Missing – AI Follow-Up")
A15: QUAL-FA | B15: 2 – Needs & Wants (Scope) | C15: FA | D15: Module Scoping | E15: Does the organization need to track, depreciate, transfer, or dispose of capital/fixed assets? | F15: Yes/No | G15: Y | I15: =IF(TRIM(H15)<>"","✓ Answered","⚠ Missing – AI Follow-Up")
A16: QUAL-CM | B16: 2 – Needs & Wants (Scope) | C16: CM | D16: Module Scoping | E16: Does the organization require bank statement reconciliation, cash positioning, or cash forecasting? | F16: Yes/No | G16: Y | I16: =IF(TRIM(H16)<>"","✓ Answered","⚠ Missing – AI Follow-Up")
A17: QUAL-MULTI | B17: 2 – Needs & Wants (Scope) | C17: GL | D17: Module Scoping | E17: Will multiple legal entities or business units require consolidated financial reporting? | F17: Yes/No | G17: Y | I17: =IF(TRIM(H17)<>"","✓ Answered","⚠ Missing – AI Follow-Up")
A18: GL-001 | B18: 3 – Detailed Discovery (Follow-Up) | C18: GL | D18: Enterprise Structure & Foundation | E18: What are the legal names, official addresses, Tax IDs, and specific statutory reporting obligations for each legal entity and business unit? | F18: Free Text | G18: Y | I18: =IF(TRIM(H18)<>"","✓ Answered",IF(G18="Y","⚠ Missing – AI Follow-Up","— Optional (not answered)"))
A19: GL-002 | B19: 3 – Detailed Discovery (Follow-Up) | C19: GL | D19: Enterprise Structure & Foundation | E19: What is your primary currency, and will you require multi-currency accounting? What accounting methods (e.g., accrual, modified accrual, cash) are required? | F19: Free Text | G19: Y | I19: =IF(TRIM(H19)<>"","✓ Answered",IF(G19="Y","⚠ Missing – AI Follow-Up","— Optional (not answered)"))
A20: GL-003 | B20: 3 – Detailed Discovery (Follow-Up) | C20: GL | D20: Enterprise Structure & Foundation | E20: What level of physical location tracking is needed (e.g., building, room), and does location data need to integrate with external systems like IT help desk or asset tracking software? | F20: Free Text | G20: N | I20: =IF(TRIM(H20)<>"","✓ Answered",IF(G20="Y","⚠ Missing – AI Follow-Up","— Optional (not answered)"))
A21: GL-004 | B21: 3 – Detailed Discovery (Follow-Up) | C21: GL | D21: Chart of Accounts (COA) & Governance | E21: Does the proposed segment structure (Fund, Cost Center, Subsidiary, Natural Account, Activity, Future 1) cover all operational and reporting needs? | F21: Free Text | G21: Y | I21: =IF(TRIM(H21)<>"","✓ Answered",IF(G21="Y","⚠ Missing – AI Follow-Up","— Optional (not answered)"))
A22: GL-005 | B22: 3 – Detailed Discovery (Follow-Up) | C22: GL | D22: Chart of Accounts (COA) & Governance | E22: Should the system allow dynamic creation of new account combinations during entry, or should all combinations be manually created and approved by Finance? | F22: Free Text | G22: Y | I22: =IF(TRIM(H22)<>"","✓ Answered",IF(G22="Y","⚠ Missing – AI Follow-Up","— Optional (not answered)"))
A23: GL-006 | B23: 3 – Detailed Discovery (Follow-Up) | C23: GL | D23: Chart of Accounts (COA) & Governance | E23: What specific cross-validation rules should exist to block invalid segment combinations (e.g., restricting certain cost centers to specific natural accounts)? Which departments need access restricted to only their specific account segments? | F23: Free Text | G23: Y | I23: =IF(TRIM(H23)<>"","✓ Answered",IF(G23="Y","⚠ Missing – AI Follow-Up","— Optional (not answered)"))
A24: GL-007 | B24: 3 – Detailed Discovery (Follow-Up) | C24: GL | D24: Chart of Accounts (COA) & Governance | E24: What is the formal workflow, approval path, or board requirement for adding new projects, funds, or segment values? | F24: Free Text | G24: Y | I24: =IF(TRIM(H24)<>"","✓ Answered",IF(G24="Y","⚠ Missing – AI Follow-Up","— Optional (not answered)"))
A25: GL-008 | B25: 3 – Detailed Discovery (Follow-Up) | C25: GL | D25: Accounting Calendar & Period Management | E25: Does your fiscal year follow the standard calendar year or a custom fiscal period? | F25: Free Text | G25: Y | I25: =IF(TRIM(H25)<>"","✓ Answered",IF(G25="Y","⚠ Missing – AI Follow-Up","— Optional (not answered)"))
A26: GL-009 | B26: 3 – Detailed Discovery (Follow-Up) | C26: GL | D26: Accounting Calendar & Period Management | E26: Do you require one adjusting period at year-end or two separate periods (e.g., one for internal year-end adjustments and one for external audit adjustments)? | F26: Free Text | G26: Y | I26: =IF(TRIM(H26)<>"","✓ Answered",IF(G26="Y","⚠ Missing – AI Follow-Up","— Optional (not answered)"))
A27: GL-010 | B27: 3 – Detailed Discovery (Follow-Up) | C27: GL | D27: Accounting Calendar & Period Management | E27: What are your policies regarding soft-closing periods, reopening prior periods, and managing future-entry statuses? | F27: Free Text | G27: Y | I27: =IF(TRIM(H27)<>"","✓ Answered",IF(G27="Y","⚠ Missing – AI Follow-Up","— Optional (not answered)"))
A28: GL-011 | B28: 3 – Detailed Discovery (Follow-Up) | C28: GL | D28: Journal Entries & Approval Workflows | E28: What types of manual journals do you enter (e.g., accruals, reclassifications, interfund billings)? | F28: Free Text | G28: Y | I28: =IF(TRIM(H28)<>"","✓ Answered",IF(G28="Y","⚠ Missing – AI Follow-Up","— Optional (not answered)"))
A29: GL-012 | B29: 3 – Detailed Discovery (Follow-Up) | C29: GL | D29: Journal Entries & Approval Workflows | E29: What are the dollar thresholds, role hierarchies, or department-specific rules that dictate who must approve a journal before posting? | F29: Free Text | G29: Y | I29: =IF(TRIM(H29)<>"","✓ Answered",IF(G29="Y","⚠ Missing – AI Follow-Up","— Optional (not answered)"))
... A92: CM-009 | B92: 3 – Detailed Discovery (Follow-Up) | C92: CM | D92: Reporting & Compliance | E92: What CM-specific reports are required (cash position, bank reconciliation status, transaction detail)? | F92: Free Text | G92: Y | I92: =IF(TRIM(H92)<>"","✓ Answered",IF(G92="Y","⚠ Missing – AI Follow-Up","— Optional (not answered)"))

Sheet Recommended Modules
A1: Module | B1: In Scope? | C1: Basis for Recommendation
A2: General Ledger (GL) | B2: ="Included – Required" | C2: ="Foundation module; required for every implementation."
A3: Accounts Payable (AP) | B3: =IF('Discovery Questions'!$H$13="Yes","Included",IF(TRIM('Discovery Questions'!$H$13)="","Pending qualifier answer","Not in scope")) | C3: ="Based on "&"QUAL-AP"&": "&IF(TRIM('Discovery Questions'!$H$13)="","not yet answered.",'Discovery Questions'!$H$13&" – "&'Discovery Questions'!$E$13)
A4: Accounts Receivable (AR) | B4: =IF('Discovery Questions'!$H$14="Yes","Included",IF(TRIM('Discovery Questions'!$H$14)="","Pending qualifier answer","Not in scope")) | C4: ="Based on "&"QUAL-AR"&": "&IF(TRIM('Discovery Questions'!$H$14)="","not yet answered.",'Discovery Questions'!$H$14&" – "&'Discovery Questions'!$E$14)
A5: Fixed Assets (FA) | B5: =IF('Discovery Questions'!$H$15="Yes","Included",IF(TRIM('Discovery Questions'!$H$15)="","Pending qualifier answer","Not in scope")) | C5: ="Based on "&"QUAL-FA"&": "&IF(TRIM('Discovery Questions'!$H$15)="","not yet answered.",'Discovery Questions'!$H$15&" – "&'Discovery Questions'!$E$15)
A6: Cash Management (CM) | B6: =IF('Discovery Questions'!$H$16="Yes","Included",IF(TRIM('Discovery Questions'!$H$16)="","Pending qualifier answer","Not in scope")) | C6: ="Based on "&"QUAL-CM"&": "&IF(TRIM('Discovery Questions'!$H$16)="","not yet answered.",'Discovery Questions'!$H$16&" – "&'Discovery Questions'!$E$16)

Sheet Cookbook Mapping
A1: Discovery Questions → OCWI GL Configuration Cookbook Mapping
A2: Built against the client-filled reference: OCWI_-_FilledOut_Oracle_Cloud_GL_Configuration_Workbook.xlsx
A4: Each row below shows which cookbook tab and field(s) a Discovery Question answer ultimately populates.
A5: This is what the AI-assisted workflow uses to auto-fill the cookbook once the questionnaire is answered.
A7: Not every Discovery Question maps to a cookbook cell — some (data conversion scope, reporting inventory,
A8: location tracking) inform the broader engagement but aren't Oracle Cloud setup fields themselves. Those
A9: are marked 'Not Mapped' with the reason, highlighted in red below.
A11: A second table further down flags cookbook tabs that currently have NO Discovery Question feeding them at
A12: all — real setup areas (Ledger, Legal Entity, Accounting Calendar detail, Journal Sources, Intercompany,
A13: budgetary control depth, etc.) the questionnaire doesn't ask about yet. Highlighted in yellow.
A15: Question ID | B15: Discovery Question (short) | C15: Cookbook Tab | D15: Cookbook Field(s) | E15: Mapping Notes
A16: QUAL-GL | B16: Is General Ledger required? | C16: (scoping only) | D16: — | E16: Gates whether this cookbook applies at all; not a cookbook field itself.
A17: INTAKE-001 | B17: Client's full legal company name | C17: Legal Entity | D17: Legal Entity Name | E17: Also seeds the Ledger tab's Description field (e.g., “Outagamie County” in the reference).
A18: GL-001 | B18: Legal names, addresses, Tax IDs, statutory reporting obligations per entity | C18: Legal Entity | D18: Legal Entity Name; Legal Entity Identifier; Address Line1/2, City, State, Postal Code; *EIN or TIN; Jurisdiction; Legal Reporting Unit Registration Number | E18: One row per legal entity. Statutory reporting obligations aren't a single field — they inform which DFFs/segment values get built (see GL-022/GL-023).
A19: GL-002 | B19: Primary currency, multi-currency requirement, accounting method | C19: Ledger; Currency; Conversion Rate Types | D19: Ledger: *Currency, *Accounting Method. Currency: per-currency Enabled flag. Conversion Rate Types: Default Rate Type, Enable Cross Rates (only if multi-currency). | E19: Single-currency clients only need the Ledger fields; multi-currency answers also drive which rows get enabled on the Currency and Conversion Rate Types tabs.
A20: GL-003 | B20: Physical location tracking level / integration with IT or asset systems | C20: — | D20: — | E20: Not Mapped — this is an HCM/Fixed Assets location-tracking concern, not a GL cookbook field.
A21: GL-004 | B21: Does the segment structure (Fund, Cost Center, Subsidiary, Natural Account, Activity, Future 1) cover all needs? | C21: Manage COA Value Sets; Manage COA Structures | D21: Value Sets: Value Set Code, Maximum Length, Uppercase Only. Structures: Segment Sequence, Name, Segment Code, Selected Label (e.g., Primary Balancing Segment, Natural Account Segment). | E21: Directly matches the COA setup tool's output — same fields, same Fusion validation rule (needs a Primary Balancing + Natural Account segment).
A22: GL-005 | B22: Dynamic account combination creation vs. Finance-approved only | C22: Manage COA Structure Instances | D22: Dynamic combination creation allowed (Yes/No) | E22: Direct 1:1 field match.
A23: GL-006 | B23: Cross-validation rules to block invalid combinations; department access restrictions | C23: Cross-Validation Rules; Segment Security | D23: CVR: Name, Condition Details, Condition Filter Segment/Values, Validation Filter Segment/Values, Error Message. Segment Security: Segment Name, Role, Tree Node for Access. | E23: Two different cookbook tabs from one discovery question — split the answer between rule logic (CVR) and role-based access (Segment Security).
A24: GL-007 | B24: Approval workflow/board requirement for adding new projects, funds, or segment values | C24: Manage COA Segment Values | D24: Enabled, Start Date, End Date (governs when a new value goes live) | E24: The approval process itself isn't a cookbook field — only its outcome (the value's effective dates) lands in the cookbook. Document the workflow in the Solution Document, not here.
A25: GL-008 | B25: Standard calendar year vs. custom fiscal period | C25: Manage Accounting Calendar | D25: Period Frequency, Start Date, Format, First Period | E25: Direct match.
A26: GL-009 | B26: One vs. two adjusting periods at year-end | C26: Manage Accounting Calendar | D26: Adjusting Period Frequency | E26: Direct match — reference shows “Twice at year end.”
... A43: GL-026 | B43: Standard financial statements and regulatory filings required out of the box | C43: — | D43: — | E43: Not Mapped — reporting deliverables are built in a separate reporting tool (e.g., FR Studio/OTBI), not this GL setup cookbook.
A46: Cookbook Tabs With No Discovery Question Yet
A47: These are real tabs in the reference cookbook that the current 26-question GL Discovery deck doesn't ask about at all. Flagging for awareness, not building out yet — extend the questionnaire when ready.
A49: Cookbook Tab | B49: What It Configures
A50: Ledger (most fields) | B50: Accounting method detail, suspense accounts, sequencing, secondary ledger, journal approval toggles, balancing threshold — the Discovery deck only covers currency and future-period policy.
A51: Manage COA Structure Instances (Displayed/Required/BI Enabled flags) | B51: Per-segment display and BI-reporting toggles beyond the dynamic-combination question.
A52: Manage COA Segment Values (bulk value load) | B52: The actual list of valid Fund/Cost Center/Account codes — no discovery question captures the client's real chart of accounts values, only the structure shape.
A53: Conversion Rate Types (detail) | B53: Cross-rate pivot currency and override settings beyond the basic multi-currency yes/no.
A54: Auto Post Criteria Sets | B54: Which journal batches post automatically vs. require manual posting action.
A55: Intercompany Balancing Rule / Transaction Types / Organization (all 3 tabs) | B55: Full intercompany setup — not touched by any current Discovery Question.
A56: Segment Hierarchies | B56: Tree/rollup structures for reporting (e.g., natural account hierarchies).
A57: Period Close Process (detail) | B57: The close checklist itself, beyond the allocation-timing question.
A58: Legal Entity (1099/registration detail) | B58: 1099 Reporting Entity flag, Legal Reporting Unit Registration Number, payroll statutory fields.

Sheet Gap Summary
A1: Section | B1: Required Questions | C1: Answered | D1: Missing (AI Follow-Up) | E1: % Complete
A2: Phase 1: Client Intake | B2: =COUNTIFS('Discovery Questions'!$C:$C,"INTAKE",'Discovery Questions'!$G:$G,"Y") | C2: =COUNTIFS('Discovery Questions'!$C:$C,"INTAKE",'Discovery Questions'!$G:$G,"Y",'Discovery Questions'!$I:$I,"✓ Answered") | D2: =COUNTIFS('Discovery Questions'!$C:$C,"INTAKE",'Discovery Questions'!$G:$G,"Y",'Discovery Questions'!$I:$I,"⚠ Missing – AI Follow-Up") | E2: =IF(B2=0,0,C2/B2)
A3: Phase 2: Needs & Wants (Scope) | B3: =COUNTIFS('Discovery Questions'!$B:$B,"2 – Needs & Wants (Scope)",'Discovery Questions'!$G:$G,"Y") | C3: =COUNTIFS('Discovery Questions'!$B:$B,"2 – Needs & Wants (Scope)",'Discovery Questions'!$G:$G,"Y",'Discovery Questions'!$I:$I,"✓ Answered") | D3: =COUNTIFS('Discovery Questions'!$B:$B,"2 – Needs & Wants (Scope)",'Discovery Questions'!$G:$G,"Y",'Discovery Questions'!$I:$I,"⚠ Missing – AI Follow-Up") | E3: =IF(B3=0,0,C3/B3)
A4: Phase 3 – General Ledger (GL) | B4: =COUNTIFS('Discovery Questions'!$C:$C,"GL",'Discovery Questions'!$B:$B,"3 – Detailed Discovery (Follow-Up)",'Discovery Questions'!$G:$G,"Y") | C4: =COUNTIFS('Discovery Questions'!$C:$C,"GL",'Discovery Questions'!$B:$B,"3 – Detailed Discovery (Follow-Up)",'Discovery Questions'!$G:$G,"Y",'Discovery Questions'!$I:$I,"✓ Answered") | D4: =COUNTIFS('Discovery Questions'!$C:$C,"GL",'Discovery Questions'!$B:$B,"3 – Detailed Discovery (Follow-Up)",'Discovery Questions'!$G:$G,"Y",'Discovery Questions'!$I:$I,"⚠ Missing – AI Follow-Up") | E4: =IF(B4=0,0,C4/B4)
A5: Phase 3 – Accounts Payable (AP) | B5: =COUNTIFS('Discovery Questions'!$C:$C,"AP",'Discovery Questions'!$B:$B,"3 – Detailed Discovery (Follow-Up)",'Discovery Questions'!$G:$G,"Y") | C5: =COUNTIFS('Discovery Questions'!$C:$C,"AP",'Discovery Questions'!$B:$B,"3 – Detailed Discovery (Follow-Up)",'Discovery Questions'!$G:$G,"Y",'Discovery Questions'!$I:$I,"✓ Answered") | D5: =COUNTIFS('Discovery Questions'!$C:$C,"AP",'Discovery Questions'!$B:$B,"3 – Detailed Discovery (Follow-Up)",'Discovery Questions'!$G:$G,"Y",'Discovery Questions'!$I:$I,"⚠ Missing – AI Follow-Up") | E5: =IF(B5=0,0,C5/B5)
A6: Phase 3 – Accounts Receivable (AR) | B6: =COUNTIFS('Discovery Questions'!$C:$C,"AR",'Discovery Questions'!$B:$B,"3 – Detailed Discovery (Follow-Up)",'Discovery Questions'!$G:$G,"Y") | C6: =COUNTIFS('Discovery Questions'!$C:$C,"AR",'Discovery Questions'!$B:$B,"3 – Detailed Discovery (Follow-Up)",'Discovery Questions'!$G:$G,"Y",'Discovery Questions'!$I:$I,"✓ Answered") | D6: =COUNTIFS('Discovery Questions'!$C:$C,"AR",'Discovery Questions'!$B:$B,"3 – Detailed Discovery (Follow-Up)",'Discovery Questions'!$G:$G,"Y",'Discovery Questions'!$I:$I,"⚠ Missing – AI Follow-Up") | E6: =IF(B6=0,0,C6/B6)
A7: Phase 3 – Fixed Assets (FA) | B7: =COUNTIFS('Discovery Questions'!$C:$C,"FA",'Discovery Questions'!$B:$B,"3 – Detailed Discovery (Follow-Up)",'Discovery Questions'!$G:$G,"Y") | C7: =COUNTIFS('Discovery Questions'!$C:$C,"FA",'Discovery Questions'!$B:$B,"3 – Detailed Discovery (Follow-Up)",'Discovery Questions'!$G:$G,"Y",'Discovery Questions'!$I:$I,"✓ Answered") | D7: =COUNTIFS('Discovery Questions'!$C:$C,"FA",'Discovery Questions'!$B:$B,"3 – Detailed Discovery (Follow-Up)",'Discovery Questions'!$G:$G,"Y",'Discovery Questions'!$I:$I,"⚠ Missing – AI Follow-Up") | E7: =IF(B7=0,0,C7/B7)
A8: Phase 3 – Cash Management (CM) | B8: =COUNTIFS('Discovery Questions'!$C:$C,"CM",'Discovery Questions'!$B:$B,"3 – Detailed Discovery (Follow-Up)",'Discovery Questions'!$G:$G,"Y") | C8: =COUNTIFS('Discovery Questions'!$C:$C,"CM",'Discovery Questions'!$B:$B,"3 – Detailed Discovery (Follow-Up)",'Discovery Questions'!$G:$G,"Y",'Discovery Questions'!$I:$I,"✓ Answered") | D8: =COUNTIFS('Discovery Questions'!$C:$C,"CM",'Discovery Questions'!$B:$B,"3 – Detailed Discovery (Follow-Up)",'Discovery Questions'!$G:$G,"Y",'Discovery Questions'!$I:$I,"⚠ Missing – AI Follow-Up") | E8: =IF(B8=0,0,C8/B8)
A9: TOTAL | B9: =SUM(B2:B8) | C9: =SUM(C2:C8) | D9: =SUM(D2:D8) | E9: =IF(B9=0,0,C9/B9)
A11: Tip: use the AutoFilter on the Discovery Questions tab (Phase or Status column) to pull the exact list of open items for the next call or for the AI to turn into follow-up questions.
